{
    "_links": {
        "self": {
            "href": "http:\/\/default\/user\/439?_format=hal_json"
        },
        "type": {
            "href": "http:\/\/drupal.org\/rest\/type\/user\/user"
        },
        "http:\/\/drupal.org\/rest\/relation\/user\/user\/profile_crm_org": [
            {
                "href": "http:\/\/default\/profile\/533?_format=hal_json"
            }
        ],
        "http:\/\/drupal.org\/rest\/relation\/user\/user\/user_picture": [
            {
                "href": "http:\/\/default\/file\/334?_format=hal_json",
                "lang": "en"
            }
        ]
    },
    "uid": [
        {
            "value": 439
        }
    ],
    "uuid": [
        {
            "value": "a398c273-5b31-4c35-b063-0c4285fbed32"
        }
    ],
    "langcode": [
        {
            "value": "en",
            "lang": "en"
        }
    ],
    "created": [
        {
            "value": 1401809388
        }
    ],
    "changed": [
        {
            "value": 1489611097,
            "lang": "en"
        }
    ],
    "default_langcode": [
        {
            "value": true,
            "lang": "en"
        }
    ],
    "_embedded": {
        "http:\/\/drupal.org\/rest\/relation\/user\/user\/profile_crm_org": [
            {
                "_links": {
                    "self": {
                        "href": "http:\/\/default\/profile\/533?_format=hal_json"
                    },
                    "type": {
                        "href": "http:\/\/drupal.org\/rest\/type\/profile\/crm_org"
                    }
                },
                "uuid": [
                    {
                        "value": "5f5d2e9a-64a7-4c5c-9591-dcb640c44d6f"
                    }
                ]
            }
        ],
        "http:\/\/drupal.org\/rest\/relation\/user\/user\/user_picture": [
            {
                "_links": {
                    "self": {
                        "href": "http:\/\/default\/file\/334?_format=hal_json"
                    },
                    "type": {
                        "href": "http:\/\/drupal.org\/rest\/type\/file\/undefined"
                    }
                },
                "uuid": [
                    {
                        "value": "f565f0aa-4495-48d3-9ed5-8c9bd8e59be2"
                    }
                ],
                "lang": "en",
                "alt": null,
                "title": null,
                "width": "680",
                "height": "173"
            }
        ]
    }
}